{
  "CURRENT_NIFTY_STRIKE": 18500,
  "CURRENT_BANKNIFTY_STRIKE": 43900,
  "NIFTY_MONTH_0_CE": 18,
  "NIFTY_MONTH_0_PE": 18,
  "BANKNIFTY_MONTH_0_CE": 38,
  "BANKNIFTY_MONTH_0_PE": 38,
  "NIFTY_MONTH_1_CE": 17,
  "NIFTY_MONTH_1_PE": 17,
  "BANKNIFTY_MONTH_1_CE": 30,
  "BANKNIFTY_MONTH_1_PE": 30,
  "NIFTY_WEEK_0_CE": 18,
  "NIFTY_WEEK_0_PE": 18,
  "BANKNIFTY_WEEK_0_CE": 38,
  "BANKNIFTY_WEEK_0_PE": 38,
  "NIFTY_WEEK_1_CE": 18,
  "NIFTY_WEEK_1_PE": 18,
  "BANKNIFTY_WEEK_1_CE": 31,
  "BANKNIFTY_WEEK_1_PE": 31,
  "NIFTY_WEEK_2_CE": 18,
  "NIFTY_WEEK_2_PE": 18,
  "BANKNIFTY_WEEK_2_CE": 30,
  "BANKNIFTY_WEEK_2_PE": 30,
  "NIFTY_WEEK_3_CE": 18,
  "NIFTY_WEEK_3_PE": 18,
  "BANKNIFTY_WEEK_3_CE": 30,
  "BANKNIFTY_WEEK_3_PE": 30
}